Metadata-Version: 1.0
Name: autocharles
Version: 1.8
Summary: Script for automating the parsing of Charles XML sessions
Home-page: http://github.com/mdiblasio/autocharles
Author: Michael DiBlasio
Author-email: mdiblasio@google.com
License: UNKNOWN
Platform: UNKNOWN
